decorit/__init__.py
decorit/decorit.py
decorit-0.2.0.dist-info/LICENSE
decorit-0.2.0.dist-info/METADATA
decorit-0.2.0.dist-info/WHEEL
decorit-0.2.0.dist-info/top_level.txt
decorit-0.2.0.dist-info/RECORD
