Metadata-Version: 2.1
Name: decorit
Version: 0.2.0
Summary: Handy ready-to-use decorators.
Home-page: https://gitlab.com/braniii/decorit
Author: braniii
License: BSD 3-Clause License
Keywords: decorators
Platform: UNKNOWN
Classifier: License :: OSI Approved :: BSD License
Classifier: Programming Language :: Python :: 3 :: Only
Classifier: Programming Language :: Python :: 3.6
Classifier: Programming Language :: Python :: 3.7
Classifier: Programming Language :: Python :: 3.8
Classifier: Programming Language :: Python :: 3.9
Classifier: Development Status :: 3 - Alpha
Requires-Dist: beartype (>=0.10.4)
Provides-Extra: all
Requires-Dist: flake8 ; extra == 'all'
Requires-Dist: pytest ; extra == 'all'
Requires-Dist: pdoc3 ; extra == 'all'
Requires-Dist: pytest-rerunfailures ; extra == 'all'
Requires-Dist: pytest-cov ; extra == 'all'
Provides-Extra: docs
Requires-Dist: pdoc3 ; extra == 'docs'
Provides-Extra: testing
Requires-Dist: pytest-cov ; extra == 'testing'
Requires-Dist: pytest ; extra == 'testing'
Requires-Dist: flake8 ; extra == 'testing'
Requires-Dist: pytest-rerunfailures ; extra == 'testing'
